jambase_api/__init__.py
jambase_api/cli.py
jambase_api/jambase.py
jambase_api/jambase_api.py
jambase_api/APISections/__init__.py
jambase_api/APISections/artists.py
jambase_api/APISections/base.py
jambase_api/APISections/events.py
jambase_api/APISections/genres.py
jambase_api/APISections/geographies.py
jambase_api/APISections/lookups.py
jambase_api/APISections/streams.py
jambase_api/APISections/venues.py
jambase_api/Classes/__init__.py
jambase_api/Classes/address.py
jambase_api/Classes/administrative_area.py
jambase_api/Classes/city.py
jambase_api/Classes/concert.py
jambase_api/Classes/country.py
jambase_api/Classes/error.py
jambase_api/Classes/event.py
jambase_api/Classes/external_identifier.py
jambase_api/Classes/festival.py
jambase_api/Classes/geo_coordinates.py
jambase_api/Classes/location.py
jambase_api/Classes/member.py
jambase_api/Classes/music_group.py
jambase_api/Classes/music_venue.py
jambase_api/Classes/offer.py
jambase_api/Classes/organization.py
jambase_api/Classes/pagination.py
jambase_api/Classes/performer.py
jambase_api/Classes/place.py
jambase_api/Classes/postal_address.py
jambase_api/Classes/price_specification.py
jambase_api/Classes/state.py
jambase_api/Classes/stream.py
jambase_api/Classes/url.py
jambase_api/Enums/__init__.py
jambase_api/Enums/artist_data_source.py
jambase_api/Enums/attendance_mode.py
jambase_api/Enums/band_or_musician.py
jambase_api/Enums/country_iso2.py
jambase_api/Enums/country_iso3.py
jambase_api/Enums/date_presets.py
jambase_api/Enums/event_data_source.py
jambase_api/Enums/event_status.py
jambase_api/Enums/event_type.py
jambase_api/Enums/festival_lineup_display_option.py
jambase_api/Enums/genre.py
jambase_api/Enums/radius_units.py
jambase_api/Enums/state.py
jambase_api/Enums/stream_data_source.py
jambase_api/Enums/url_type.py
jambase_api/Enums/venue_data_source.py
jambase_api/ParameterTypes/__init__.py
jambase_api/ParameterTypes/artist_search.py
jambase_api/ParameterTypes/event_search.py
jambase_api-1.0.0.dist-info/LICENSE
jambase_api-1.0.0.dist-info/METADATA
jambase_api-1.0.0.dist-info/WHEEL
jambase_api-1.0.0.dist-info/top_level.txt
jambase_api-1.0.0.dist-info/RECORD
