Metadata-Version: 2.1
Name: jambase-api
Version: 1.0.0
Summary: Python API wrapper for Jambase API
Home-page: https://github.com/eswedick/jambase_api
Author: Evan Swedick
Author-email: eswedick@gmail.com
License: MIT
Requires-Python: >=3.9
License-File: LICENSE
Requires-Dist: requests ==2.31.0
